[
  {
    "id": 1,
    "name": "Antares",
    "description": "Cerveceria en Cordoba",
    "urlImagen": "/publicidad-antares.webp"
  },
  {
    "id": 2,
    "name": "Dulce coco",
    "description": "Estetica en Cordoba",
    "urlImagen": "/publicidad-dulcecoco.webp"
  },
  {
    "id": 3,
    "name": "Holiday Inn",
    "description": "Hotel en Cordoba",
    "urlImagen": "/publicidad-holidayinn.webp"
  },
  {
    "id": 4,
    "name": "Hermanos Luci",
    "description": "Miel en Cordoba",
    "urlImagen": "/publicidad-hermanosluci.webp"
  }
]
